{"name":"NBSB PK Jeugd 2025/26 C","number_of_rounds":7,"players":[{"federation":"NED","flags":"","gender":"M","id":"8809306","name":"Leenen, Boyd","official_rating":true,"pairing_number":1,"rating":2096},{"federation":"NED","flags":"","gender":"M","id":"8973327","name":"Huang, Vincent","official_rating":true,"pairing_number":2,"rating":1883},{"federation":"NED","flags":"","gender":"M","id":"8990377","name":"Zhou, Yanyang","official_rating":true,"pairing_number":3,"rating":1867},{"federation":"NED","flags":"","gender":"M","id":"8930592","name":"Lalkota, Sai Pranav Tejas","official_rating":true,"pairing_number":4,"rating":1849},{"federation":"NED","flags":"","gender":"M","id":"8924927","name":"Verstegen, Jonas","official_rating":true,"pairing_number":5,"rating":1830},{"federation":"NED","flags":"","gender":"M","id":"9028008","name":"Bruls, Sven","official_rating":true,"pairing_number":6,"rating":1784},{"federation":"NED","flags":"","gender":"M","id":"8890805","name":"Van Houtert, Lennart","official_rating":true,"pairing_number":7,"rating":1737},{"federation":"NED","flags":"","gender":"M","id":"8746727","name":"Zhang, Eric","official_rating":true,"pairing_number":8,"rating":1505},{"federation":"NED","flags":"","gender":"M","id":"9021133","name":"Methlouthi, Aly","official_rating":true,"pairing_number":9,"rating":1386},{"federation":"NED","flags":"","gender":"M","id":"8974768","name":"Lalkota, Srikar","official_rating":true,"pairing_number":10,"rating":1334},{"federation":"NED","flags":"","gender":"M","id":"9013829","name":"Khuat Duy, Vincent","official_rating":true,"pairing_number":11,"rating":0},{"federation":"NED","flags":"","gender":"M","id":"8902355","name":"Leenen, Bing","official_rating":true,"pairing_number":12,"rating":0},{"federation":"NED","flags":"","gender":"M","id":"9093799","name":"Morgan, Finn","official_rating":true,"pairing_number":13,"rating":0},{"federation":"NED","flags":"","gender":"M","id":"9100630","name":"Vinothkumar, Dhanvanth","official_rating":true,"pairing_number":14,"rating":0}],"rounds":[{"byes":[],"date":"2025-12-27","number":1,"pairings":[{"black":1,"black_points":1.0,"table":1,"white":8,"white_points":0.0},{"black":9,"black_points":0.0,"table":2,"white":2,"white_points":1.0},{"black":3,"black_points":1.0,"table":3,"white":10,"white_points":0.0},{"black":11,"black_points":0.0,"table":4,"white":4,"white_points":1.0},{"black":5,"black_points":0.5,"table":5,"white":12,"white_points":0.5},{"black":13,"black_points":0.0,"table":6,"white":6,"white_points":1.0},{"black":7,"black_points":1.0,"forfeit":true,"table":7,"white":14,"white_points":0.0}],"ranking":[{"average_rating_cut":1505.0,"buchholz":0.0,"buchholz_cut":0.0,"color_balance":-1,"mutual_result_top":0.0,"player":1,"progressive_score":1.0,"rank":1,"score":1.0,"sonneborn_berger":0.0,"tpr":2496,"tpr_mixed":2305,"w_we":0.08},{"average_rating_cut":1386.0,"buchholz":0.0,"buchholz_cut":0.0,"color_balance":1,"mutual_result_top":0.0,"player":2,"progressive_score":1.0,"rank":2,"score":1.0,"sonneborn_berger":0.0,"tpr":2283,"tpr_mixed":2186,"w_we":0.08},{"average_rating_cut":1334.0,"buchholz":0.0,"buchholz_cut":0.0,"color_balance":-1,"mutual_result_top":0.0,"player":3,"progressive_score":1.0,"rank":3,"score":1.0,"sonneborn_berger":0.0,"tpr":2267,"tpr_mixed":2134,"w_we":0.08},{"average_rating_cut":1000.0,"buchholz":0.0,"buchholz_cut":0.0,"color_balance":1,"mutual_result_top":0.0,"player":4,"progressive_score":1.0,"rank":4,"score":1.0,"sonneborn_berger":0.0,"tpr":0,"tpr_mixed":0,"w_we":0.0},{"average_rating_cut":1000.0,"buchholz":0.0,"buchholz_cut":0.0,"color_balance":1,"mutual_result_top":0.0,"player":6,"progressive_score":1.0,"rank":5,"score":1.0,"sonneborn_berger":0.0,"tpr":0,"tpr_mixed":0,"w_we":0.0},{"average_rating_cut":0.0,"buchholz":0.0,"buchholz_cut":0.0,"color_balance":-1,"mutual_result_top":0.0,"player":7,"progressive_score":1.0,"rank":6,"score":1.0,"sonneborn_berger":0.0,"tpr":0,"tpr_mixed":0,"w_we":0.0},{"average_rating_cut":1000.0,"buchholz":0.5,"buchholz_cut":0.5,"color_balance":-1,"player":5,"progressive_score":0.5,"rank":7,"score":0.5,"sonneborn_berger":0.25,"tpr":0,"tpr_mixed":0,"w_we":0.0},{"average_rating_cut":1830.0,"buchholz":0.5,"buchholz_cut":0.5,"color_balance":1,"player":12,"progressive_score":0.5,"rank":8,"score":0.5,"sonneborn_berger":0.25,"tpr":1830,"tpr_mixed":1830},{"average_rating_cut":2096.0,"buchholz":1.0,"buchholz_cut":1.0,"color_balance":1,"player":8,"progressive_score":0.0,"rank":9,"score":0.0,"sonneborn_berger":0.0,"tpr":1105,"tpr_mixed":1296,"w_we":-0.08},{"average_rating_cut":1883.0,"buchholz":1.0,"buchholz_cut":1.0,"color_balance":-1,"player":9,"progressive_score":0.0,"rank":10,"score":0.0,"sonneborn_berger":0.0,"tpr":986,"tpr_mixed":1083,"w_we":-0.08},{"average_rating_cut":1867.0,"buchholz":1.0,"buchholz_cut":1.0,"color_balance":1,"player":10,"progressive_score":0.0,"rank":11,"score":0.0,"sonneborn_berger":0.0,"tpr":934,"tpr_mixed":1067,"w_we":-0.08},{"average_rating_cut":1849.0,"buchholz":1.0,"buchholz_cut":1.0,"color_balance":-1,"player":11,"progressive_score":0.0,"rank":12,"score":0.0,"sonneborn_berger":0.0,"tpr":1049,"tpr_mixed":1049},{"average_rating_cut":1784.0,"buchholz":1.0,"buchholz_cut":1.0,"color_balance":-1,"player":13,"progressive_score":0.0,"rank":13,"score":0.0,"sonneborn_berger":0.0,"tpr":984,"tpr_mixed":984},{"average_rating_cut":0.0,"buchholz":1.0,"buchholz_cut":1.0,"color_balance":1,"player":14,"progressive_score":0.0,"rank":14,"score":0.0,"sonneborn_berger":0.0,"tpr":0,"tpr_mixed":0}]},{"byes":[],"date":"2025-12-27","number":2,"pairings":[{"black":4,"table":1,"white":1},{"black":2,"table":2,"white":7},{"black":6,"table":3,"white":3},{"black":8,"table":4,"white":5},{"black":12,"table":5,"white":9},{"black":10,"table":6,"white":13},{"black":14,"table":7,"white":11}],"ranking":[{"average_rating_cut":1883.0,"buchholz":0.5,"buchholz_cut":0.5,"color_balance":0,"mutual_result_top":0.0,"player":7,"progressive_score":1.0,"rank":1,"score":1.0,"sonneborn_berger":0.5,"tpr":0,"tpr_mixed":0,"w_we":0.0},{"average_rating_cut":1677.0,"buchholz":0.0,"buchholz_cut":0.0,"color_balance":0,"mutual_result_top":0.0,"player":1,"progressive_score":1.0,"rank":2,"score":1.0,"sonneborn_berger":0.0,"tpr":2496,"tpr_mixed":2305,"w_we":0.08},{"average_rating_cut":1561.5,"buchholz":0.0,"buchholz_cut":0.0,"color_balance":0,"mutual_result_top":0.0,"player":2,"progressive_score":1.0,"rank":3,"score":1.0,"sonneborn_berger":0.0,"tpr":2283,"tpr_mixed":2186,"w_we":0.08},{"average_rating_cut":1559.0,"buchholz":0.0,"buchholz_cut":0.0,"color_balance":0,"mutual_result_top":0.0,"player":3,"progressive_score":1.0,"rank":4,"score":1.0,"sonneborn_berger":0.0,"tpr":2267,"tpr_mixed":2134,"w_we":0.08},{"average_rating_cut":1548.0,"buchholz":0.0,"buchholz_cut":0.0,"color_balance":0,"mutual_result_top":0.0,"player":4,"progressive_score":1.0,"rank":5,"score":1.0,"sonneborn_berger":0.0,"tpr":0,"tpr_mixed":0,"w_we":0.0},{"average_rating_cut":1433.5,"buchholz":0.0,"buchholz_cut":0.0,"color_balance":0,"mutual_result_top":0.0,"player":6,"progressive_score":1.0,"rank":6,"score":1.0,"sonneborn_berger":0.0,"tpr":0,"tpr_mixed":0,"w_we":0.0},{"average_rating_cut":1252.5,"buchholz":0.5,"buchholz_cut":0.5,"color_balance":0,"player":5,"progressive_score":0.5,"rank":7,"score":0.5,"sonneborn_berger":0.25,"tpr":0,"tpr_mixed":0,"w_we":0.0},{"average_rating_cut":1608.0,"buchholz":0.5,"buchholz_cut":0.5,"color_balance":0,"player":12,"progressive_score":0.5,"rank":8,"score":0.5,"sonneborn_berger":0.25,"tpr":1830,"tpr_mixed":1830},{"average_rating_cut":1000.0,"buchholz":1.5,"buchholz_cut":1.5,"color_balance":0,"player":14,"progressive_score":0.0,"rank":9,"score":0.0,"sonneborn_berger":0.0,"tpr":0,"tpr_mixed":0},{"average_rating_cut":1963.0,"buchholz":1.0,"buchholz_cut":1.0,"color_balance":0,"player":8,"progressive_score":0.0,"rank":10,"score":0.0,"sonneborn_berger":0.0,"tpr":1105,"tpr_mixed":1296,"w_we":-0.08},{"average_rating_cut":1441.5,"buchholz":1.0,"buchholz_cut":1.0,"color_balance":0,"player":9,"progressive_score":0.0,"rank":11,"score":0.0,"sonneborn_berger":0.0,"tpr":986,"tpr_mixed":1083,"w_we":-0.08},{"average_rating_cut":1433.5,"buchholz":1.0,"buchholz_cut":1.0,"color_balance":0,"player":10,"progressive_score":0.0,"rank":12,"score":0.0,"sonneborn_berger":0.0,"tpr":934,"tpr_mixed":1067,"w_we":-0.08},{"average_rating_cut":1424.5,"buchholz":1.0,"buchholz_cut":1.0,"color_balance":0,"player":11,"progressive_score":0.0,"rank":13,"score":0.0,"sonneborn_berger":0.0,"tpr":1049,"tpr_mixed":1049},{"average_rating_cut":1559.0,"buchholz":1.0,"buchholz_cut":1.0,"color_balance":0,"player":13,"progressive_score":0.0,"rank":14,"score":0.0,"sonneborn_berger":0.0,"tpr":984,"tpr_mixed":984}]}],"tiebreaks":["score","buchholz","sonneborn_berger","rating"],"updated_at":"2025-12-27T10:36:22Z"}